pypbs3/__init__.py
pypbs3-0.0.1.dist-info/LICENSE
pypbs3-0.0.1.dist-info/METADATA
pypbs3-0.0.1.dist-info/WHEEL
pypbs3-0.0.1.dist-info/top_level.txt
pypbs3-0.0.1.dist-info/RECORD
