Metadata-Version: 2.1
Name: pypbs3
Version: 0.0.1
Summary: Handle proxmox backup server operations via api
Home-page: https://github.com/gizmo15/pypbs3
Author: Boris Tassou
Author-email: boris.tassou@securmail.fr
Project-URL: Bug Tracker, https://github.com/gizmo15/pypbs3/issues
Classifier: Programming Language :: Python :: 3
Classifier: License :: OSI Approved :: GNU General Public License v3 or later (GPLv3+)
Classifier: Operating System :: OS Independent
Requires-Python: >=3
License-File: LICENSE
Requires-Dist: requests
